Metadata-Version: 2.1
Name: boto3
Version: 1.42.39
Summary: The AWS SDK for Python
Home-page: https://github.com/boto/boto3
Author: Amazon Web Services
License: Apache-2.0
Project-URL: Documentation, https://boto3.amazonaws.com/v1/documentation/api/latest/index.html
Project-URL: Source, https://github.com/boto/boto3
Classifier: Development Status :: 5 - Production/Stable
Classifier: Intended Audience :: Developers
Classifier: Natural Language :: English
Classifier: Programming Language :: Python
Classifier: Programming Language :: Python :: 3
Classifier: Programming Language :: Python :: 3 :: Only
Classifier: Programming Language :: Python :: 3.9
Classifier: Programming Language :: Python :: 3.10
Classifier: Programming Language :: Python :: 3.11
Classifier: Programming Language :: Python :: 3.12
Classifier: Programming Language :: Python :: 3.13
Classifier: Programming Language :: Python :: 3.14
Requires-Python: >= 3.9
License-File: LICENSE
License-File: NOTICE
Requires-Dist: botocore<1.43.0,>=1.42.39
Requires-Dist: jmespath<2.0.0,>=0.7.1
Requires-Dist: s3transfer<0.17.0,>=0.16.0
Provides-Extra: crt
Requires-Dist: botocore[crt]<2.0a0,>=1.21.0; extra == "crt"
